tclambda/__init__.py
tclambda/auto_functions.py
tclambda/exceptions.py
tclambda/extras.py
tclambda/function.py
tclambda/handlers.py
tclambda/messages.py
tclambda-0.0.12.dist-info/LICENSE
tclambda-0.0.12.dist-info/WHEEL
tclambda-0.0.12.dist-info/METADATA
tclambda-0.0.12.dist-info/RECORD
