Metadata-Version: 2.1
Name: tclambda
Version: 0.0.12
Summary: AWS Lambda Library
Home-page: https://github.com/trustcruit/tclambda
License: UNKNOWN
Author: Niels Lemmens
Author-email: draso.odin@gmail.com
Requires-Python: >=3.7
Classifier: Development Status :: 2 - Pre-Alpha
Classifier: License :: OSI Approved :: MIT License
Classifier: Programming Language :: Python :: 3.7
Classifier: Topic :: Software Development :: Libraries :: Python Modules
Requires-Dist: sentry-sdk >=0.8,<1.0 ; extra == "sentry"
Provides-Extra: sentry
